hypixel_api/__init__.py
hypixel_api/api.py
hypixel_api/exceptions.py
hypixel_api/guild.py
hypixel_api/player.py
hypixel_api/utilities.py
hypixel_api_py-0.0.0.0.1.dist-info/LICENSE
hypixel_api_py-0.0.0.0.1.dist-info/METADATA
hypixel_api_py-0.0.0.0.1.dist-info/WHEEL
hypixel_api_py-0.0.0.0.1.dist-info/top_level.txt
hypixel_api_py-0.0.0.0.1.dist-info/RECORD
