Metadata-Version: 2.1
Name: hypixel-api-py
Version: 0.0.0.0.1
Summary: A Python Package to interact with the Hypixel API
Author-email: GBG <idkletmeinnow@gmail.com>
License: Copyright (c) 2022 GBG        
Project-URL: Homepage, https://github.com/GreenBoyGreen/Hypixel-Api
Project-URL: Bug Tracker, https://github.com/GreenBoyGreen/Hypixel-Api/issues
Classifier: Programming Language :: Python :: 3
Classifier: License :: OSI Approved :: MIT License
Classifier: Operating System :: OS Independent
Requires-Python: >=3.7
License-File: LICENSE
Requires-Dist: requests (>=2.28.1)
